aiddl_core/__init__.py
aiddl_core/aiddl/__init__.py
aiddl_core/aiddl/org/__init__.py
aiddl_core/aiddl/org/aiddl/__init__.py
aiddl_core/aiddl/org/aiddl/eval-ht.aiddl
aiddl_core/aiddl/org/aiddl/eval.aiddl
aiddl_core/aiddl/org/aiddl/core/__init__.py
aiddl_core/aiddl/org/aiddl/core/util/__init__.py
aiddl_core/aiddl/org/aiddl/core/util/math.aiddl
aiddl_core/aiddl/org/aiddl/core/util/random.aiddl
aiddl_core/aiddl/org/aiddl/core/util/request.aiddl
aiddl_core/aiddl/org/aiddl/eval/__init__.py
aiddl_core/aiddl/org/aiddl/eval/namespace.aiddl
aiddl_core/aiddl/org/aiddl/util/__init__.py
aiddl_core/aiddl/org/aiddl/util/math.aiddl
aiddl_core/aiddl/org/aiddl/util/random.aiddl
aiddl_core/aiddl/org/aiddl/util/request.aiddl
aiddl_core/container/__init__.py
aiddl_core/container/container.py
aiddl_core/container/entry.py
aiddl_core/container/module.py
aiddl_core/function/__init__.py
aiddl_core/function/default.py
aiddl_core/function/evaluator.py
aiddl_core/function/function.py
aiddl_core/function/function_registry.py
aiddl_core/function/eval/__init__.py
aiddl_core/function/eval/collection.py
aiddl_core/function/eval/higher_order.py
aiddl_core/function/eval/logic.py
aiddl_core/function/eval/misc.py
aiddl_core/function/eval/numerical.py
aiddl_core/function/eval/python.py
aiddl_core/function/eval/string.py
aiddl_core/function/eval/type.py
aiddl_core/parser/__init__.py
aiddl_core/parser/checks.py
aiddl_core/parser/parser.py
aiddl_core/parser/simple_stack.py
aiddl_core/parser/tokens.py
aiddl_core/parser/util.py
aiddl_core/representation/__init__.py
aiddl_core/representation/collection.py
aiddl_core/representation/entref.py
aiddl_core/representation/funref.py
aiddl_core/representation/inf.py
aiddl_core/representation/int.py
aiddl_core/representation/keyval.py
aiddl_core/representation/list.py
aiddl_core/representation/nan.py
aiddl_core/representation/num.py
aiddl_core/representation/rat.py
aiddl_core/representation/real.py
aiddl_core/representation/set.py
aiddl_core/representation/str.py
aiddl_core-0.3.7.dist-info/LICENSE
aiddl_core-0.3.7.dist-info/METADATA
aiddl_core-0.3.7.dist-info/WHEEL
aiddl_core-0.3.7.dist-info/top_level.txt
aiddl_core-0.3.7.dist-info/RECORD
