Metadata-Version: 2.1
Name: aiddl-core
Version: 0.3.7
Summary: Core Library for the AI Domain Definition Language (AIDDL) Framework for Integrative AI
Home-page: http://www.aiddl.org
Author: Uwe Köckemann
Author-email: uwe.kockemann@oru.se
License: UNKNOWN
Project-URL: Bug Tracker, https://github.com/uwe-koeckemann/AIDDL/issues
Platform: UNKNOWN
Classifier: Programming Language :: Python :: 3
Classifier: License :: OSI Approved :: MIT License
Classifier: Operating System :: OS Independent
Requires-Python: >=3.7
License-File: LICENSE
